src/pe.v
module pe #(parameter DATA_WIDTH = 16)
(
    input wire clk,
    input wire reset,
    input wire [DATA_WIDTH-1:0] a_in,
    input wire [DATA_WIDTH-1:0] b_in,
    input wire valid_in,
    output reg valid_out,
    output reg [DATA_WIDTH-1:0] a_out,
    output reg [DATA_WIDTH-1:0] b_out,
    output reg [2*DATA_WIDTH-1:0] c_out
);

    wire [2*DATA_WIDTH-1:0] mult; //balatro
    //mult
    assign mult = a_in * b_in;

    //keep moving 
    always @(posedge clk) begin
        if (reset) begin
            c_out <= 0;
            valid_out <= 0;
        end
        else begin
            a_out <= a_in;
            b_out <= b_in;
            valid_out <= valid_in;

            if (valid_in) begin
                c_out <= c_out + mult;  //add chips due to chips * mult
            end
        end
    end

endmodule

src/systolic_array_4x4.v
`timescale 1ns/1ps

module systolic_array_4x4 #(
    parameter DATA_WIDTH = 16
)(
    input  wire                        clk,
    input  wire                        reset,

    // Input streams for A and B
    input  wire [DATA_WIDTH-1:0]       a_in_row [0:3], // row-wise A inputs
    input  wire [DATA_WIDTH-1:0]       b_in_col [0:3], // column-wise B inputs
    input  wire                        valid_in,

    // Output C matrix (each PE's c_out)
    output wire [2*DATA_WIDTH-1:0]     c_out [0:3][0:3],
    output wire                        valid_out
);
    wire [DATA_WIDTH-1:0] a_wire [0:3][0:3];
    wire [DATA_WIDTH-1:0] b_wire [0:3][0:3];
    wire valid_wire [0:3][0:3];

    genvar i;
    genvar j;
    for (i = 0; i < 4; i = i + 1) begin : ROW
        for (j = 0; j < 4; j = j + 1) begin : COL
            wire [DATA_WIDTH-1:0] a_in_local;
            wire [DATA_WIDTH-1:0] b_in_local;
            wire valid_in_local;
            //A
            if (j == 0)
                assign a_in_local = a_in_row[i];
            else
                assign a_in_local = a_wire[i][j-1];

            //B
            if (i == 0)
                assign b_in_local = b_in_col[j];
            else
                assign b_in_local = b_wire[i-1][j];

            //propagate
            if (i == 0 && j == 0)
                assign valid_in_local = valid_in;
            else if (j == 0)
                assign valid_in_local = valid_wire[i-1][j];
            else
                assign valid_in_local = valid_wire[i][j-1];
            //pe           
            pe #(
                .DATA_WIDTH(DATA_WIDTH)
            ) pe_inst (
                .clk(clk),
                .reset(reset),
                .a_in(a_in_local),
                .b_in(b_in_local),
                .valid_in(valid_in_local),
                .valid_out(valid_wire[i][j]),
                .a_out(a_wire[i][j]),
                .b_out(b_wire[i][j]),
                .c_out(c_out[i][j])
            );
        end
    end
    //end reached
    assign valid_out = valid_wire[3][3];

endmodule

tests/systolic_array_4x4_wavetest_tb.v
`timescale 1ns/1ps

module systolic_array_4x4_tb;

    parameter DATA_WIDTH = 16;

    reg clk;
    reg reset;
    reg valid_in;

    reg  [DATA_WIDTH-1:0] a_in_row [0:3];
    reg  [DATA_WIDTH-1:0] b_in_col [0:3];

    wire [2*DATA_WIDTH-1:0] c_out [0:3][0:3];
    wire valid_out;

    systolic_array_4x4 #(
        .DATA_WIDTH(DATA_WIDTH)
    ) 
    dut (
        .clk(clk),
        .reset(reset),
        .a_in_row(a_in_row),
        .b_in_col(b_in_col),
        .valid_in(valid_in),
        .c_out(c_out),
        .valid_out(valid_out)
    );

    // Clock
    always #5 clk = ~clk;

    integer i;

    initial begin
        $dumpfile("4x4_dump.vcd");
        $dumpvars(0, systolic_array_4x4_tb);

        clk = 0;
        reset = 1;
        valid_in = 0;

        for (i = 0; i < 4; i = i + 1) begin
            a_in_row[i] = 0;
            b_in_col[i] = 0;
        end

        #20;
        reset = 0;

        // begin
        @(posedge clk);
        valid_in = 1;
        //mat a
        a_in_row[0] = 1;
        a_in_row[1] = 2;
        a_in_row[2] = 3;
        a_in_row[3] = 4;
        //mat b
        b_in_col[0] = 5;
        b_in_col[1] = 6;
        b_in_col[2] = 7;
        b_in_col[3] = 8;

        @(posedge clk);
        valid_in = 0;

        // wait like 12 times
        repeat (12) @(posedge clk);
        $display("Bottom-right PE C value: %d", c_out[3][3]);
        $finish;
    end

endmodule

4x4_dump.vcd
$date
	Thu Mar 12 23:59:27 2026
$end
$version
	Icarus Verilog
$end
$timescale
	1ps
$end
$scope module systolic_array_4x4_tb $end
$var wire 1 ! valid_out $end
$var parameter 32 " DATA_WIDTH $end
$var reg 1 # clk $end
$var reg 1 $ reset $end
$var reg 1 % valid_in $end
$var integer 32 & i [31:0] $end
$scope module dut $end
$var wire 1 # clk $end
$var wire 1 $ reset $end
$var wire 1 % valid_in $end
$var wire 1 ! valid_out $end
$var parameter 32 ' DATA_WIDTH $end
$scope begin ROW[0] $end
$var parameter 2 ( i $end
$scope begin COL[0] $end
$var wire 1 ) valid_in_local $end
$var wire 16 * b_in_local [15:0] $end
$var wire 16 + a_in_local [15:0] $end
$var parameter 2 , j $end
$scope begin genblk1 $end
$upscope $end
$scope begin genblk2 $end
$upscope $end
$scope begin genblk3 $end
$upscope $end
$scope module pe_inst $end
$var wire 16 - a_in [15:0] $end
$var wire 16 . b_in [15:0] $end
$var wire 1 # clk $end
$var wire 1 $ reset $end
$var wire 1 ) valid_in $end
$var wire 32 / mult [31:0] $end
$var parameter 32 0 DATA_WIDTH $end
$var reg 16 1 a_out [15:0] $end
$var reg 16 2 b_out [15:0] $end
$var reg 32 3 c_out [31:0] $end
$var reg 1 4 valid_out $end
$upscope $end
$upscope $end
$scope begin COL[1] $end
$var wire 1 5 valid_in_local $end
$var wire 16 6 b_in_local [15:0] $end
$var wire 16 7 a_in_local [15:0] $end
$var parameter 2 8 j $end
$scope begin genblk1 $end
$upscope $end
$scope begin genblk2 $end
$upscope $end
$scope begin genblk3 $end
$upscope $end
$scope module pe_inst $end
$var wire 16 9 a_in [15:0] $end
$var wire 16 : b_in [15:0] $end
$var wire 1 # clk $end
$var wire 1 $ reset $end
$var wire 1 5 valid_in $end
$var wire 32 ; mult [31:0] $end
$var parameter 32 < DATA_WIDTH $end
$var reg 16 = a_out [15:0] $end
$var reg 16 > b_out [15:0] $end
$var reg 32 ? c_out [31:0] $end
$var reg 1 @ valid_out $end
$upscope $end
$upscope $end
$scope begin COL[2] $end
$var wire 1 A valid_in_local $end
$var wire 16 B b_in_local [15:0] $end
$var wire 16 C a_in_local [15:0] $end
$var parameter 3 D j $end
$scope begin genblk1 $end
$upscope $end
$scope begin genblk2 $end
$upscope $end
$scope begin genblk3 $end
$upscope $end
$scope module pe_inst $end
$var wire 16 E a_in [15:0] $end
$var wire 16 F b_in [15:0] $end
$var wire 1 # clk $end
$var wire 1 $ reset $end
$var wire 1 A valid_in $end
$var wire 32 G mult [31:0] $end
$var parameter 32 H DATA_WIDTH $end
$var reg 16 I a_out [15:0] $end
$var reg 16 J b_out [15:0] $end
$var reg 32 K c_out [31:0] $end
$var reg 1 L valid_out $end
$upscope $end
$upscope $end
$scope begin COL[3] $end
$var wire 1 M valid_in_local $end
$var wire 16 N b_in_local [15:0] $end
$var wire 16 O a_in_local [15:0] $end
$var parameter 3 P j $end
$scope begin genblk1 $end
$upscope $end
$scope begin genblk2 $end
$upscope $end
$scope begin genblk3 $end
$upscope $end
$scope module pe_inst $end
$var wire 16 Q a_in [15:0] $end
$var wire 16 R b_in [15:0] $end
$var wire 1 # clk $end
$var wire 1 $ reset $end
$var wire 1 M valid_in $end
$var wire 32 S mult [31:0] $end
$var parameter 32 T DATA_WIDTH $end
$var reg 16 U a_out [15:0] $end
$var reg 16 V b_out [15:0] $end
$var reg 32 W c_out [31:0] $end
$var reg 1 X valid_out $end
$upscope $end
$upscope $end
$upscope $end
$scope begin ROW[1] $end
$var parameter 2 Y i $end
$scope begin COL[0] $end
$var wire 1 Z valid_in_local $end
$var wire 16 [ b_in_local [15:0] $end
$var wire 16 \ a_in_local [15:0] $end
$var parameter 2 ] j $end
$scope begin genblk1 $end
$upscope $end
$scope begin genblk2 $end
$upscope $end
$scope begin genblk3 $end
$upscope $end
$scope module pe_inst $end
$var wire 16 ^ a_in [15:0] $end
$var wire 16 _ b_in [15:0] $end
$var wire 1 # clk $end
$var wire 1 $ reset $end
$var wire 1 Z valid_in $end
$var wire 32 ` mult [31:0] $end
$var parameter 32 a DATA_WIDTH $end
$var reg 16 b a_out [15:0] $end
$var reg 16 c b_out [15:0] $end
$var reg 32 d c_out [31:0] $end
$var reg 1 e valid_out $end
$upscope $end
$upscope $end
$scope begin COL[1] $end
$var wire 1 f valid_in_local $end
$var wire 16 g b_in_local [15:0] $end
$var wire 16 h a_in_local [15:0] $end
$var parameter 2 i j $end
$scope begin genblk1 $end
$upscope $end
$scope begin genblk2 $end
$upscope $end
$scope begin genblk3 $end
$upscope $end
$scope module pe_inst $end
$var wire 16 j a_in [15:0] $end
$var wire 16 k b_in [15:0] $end
$var wire 1 # clk $end
$var wire 1 $ reset $end
$var wire 1 f valid_in $end
$var wire 32 l mult [31:0] $end
$var parameter 32 m DATA_WIDTH $end
$var reg 16 n a_out [15:0] $end
$var reg 16 o b_out [15:0] $end
$var reg 32 p c_out [31:0] $end
$var reg 1 q valid_out $end
$upscope $end
$upscope $end
$scope begin COL[2] $end
$var wire 1 r valid_in_local $end
$var wire 16 s b_in_local [15:0] $end
$var wire 16 t a_in_local [15:0] $end
$var parameter 3 u j $end
$scope begin genblk1 $end
$upscope $end
$scope begin genblk2 $end
$upscope $end
$scope begin genblk3 $end
$upscope $end
$scope module pe_inst $end
$var wire 16 v a_in [15:0] $end
$var wire 16 w b_in [15:0] $end
$var wire 1 # clk $end
$var wire 1 $ reset $end
$var wire 1 r valid_in $end
$var wire 32 x mult [31:0] $end
$var parameter 32 y DATA_WIDTH $end
$var reg 16 z a_out [15:0] $end
$var reg 16 { b_out [15:0] $end
$var reg 32 | c_out [31:0] $end
$var reg 1 } valid_out $end
$upscope $end
$upscope $end
$scope begin COL[3] $end
$var wire 1 ~ valid_in_local $end
$var wire 16 !" b_in_local [15:0] $end
$var wire 16 "" a_in_local [15:0] $end
$var parameter 3 #" j $end
$scope begin genblk1 $end
$upscope $end
$scope begin genblk2 $end
$upscope $end
$scope begin genblk3 $end
$upscope $end
$scope module pe_inst $end
$var wire 16 $" a_in [15:0] $end
$var wire 16 %" b_in [15:0] $end
$var wire 1 # clk $end
$var wire 1 $ reset $end
$var wire 1 ~ valid_in $end
$var wire 32 &" mult [31:0] $end
$var parameter 32 '" DATA_WIDTH $end
$var reg 16 (" a_out [15:0] $end
$var reg 16 )" b_out [15:0] $end
$var reg 32 *" c_out [31:0] $end
$var reg 1 +" valid_out $end
$upscope $end
$upscope $end
$upscope $end
$scope begin ROW[2] $end
$var parameter 3 ," i $end
$scope begin COL[0] $end
$var wire 1 -" valid_in_local $end
$var wire 16 ." b_in_local [15:0] $end
$var wire 16 /" a_in_local [15:0] $end
$var parameter 2 0" j $end
$scope begin genblk1 $end
$upscope $end
$scope begin genblk2 $end
$upscope $end
$scope begin genblk3 $end
$upscope $end
$scope module pe_inst $end
$var wire 16 1" a_in [15:0] $end
$var wire 16 2" b_in [15:0] $end
$var wire 1 # clk $end
$var wire 1 $ reset $end
$var wire 1 -" valid_in $end
$var wire 32 3" mult [31:0] $end
$var parameter 32 4" DATA_WIDTH $end
$var reg 16 5" a_out [15:0] $end
$var reg 16 6" b_out [15:0] $end
$var reg 32 7" c_out [31:0] $end
$var reg 1 8" valid_out $end
$upscope $end
$upscope $end
$scope begin COL[1] $end
$var wire 1 9" valid_in_local $end
$var wire 16 :" b_in_local [15:0] $end
$var wire 16 ;" a_in_local [15:0] $end
$var parameter 2 <" j $end
$scope begin genblk1 $end
$upscope $end
$scope begin genblk2 $end
$upscope $end
$scope begin genblk3 $end
$upscope $end
$scope module pe_inst $end
$var wire 16 =" a_in [15:0] $end
$var wire 16 >" b_in [15:0] $end
$var wire 1 # clk $end
$var wire 1 $ reset $end
$var wire 1 9" valid_in $end
$var wire 32 ?" mult [31:0] $end
$var parameter 32 @" DATA_WIDTH $end
$var reg 16 A" a_out [15:0] $end
$var reg 16 B" b_out [15:0] $end
$var reg 32 C" c_out [31:0] $end
$var reg 1 D" valid_out $end
$upscope $end
$upscope $end
$scope begin COL[2] $end
$var wire 1 E" valid_in_local $end
$var wire 16 F" b_in_local [15:0] $end
$var wire 16 G" a_in_local [15:0] $end
$var parameter 3 H" j $end
$scope begin genblk1 $end
$upscope $end
$scope begin genblk2 $end
$upscope $end
$scope begin genblk3 $end
$upscope $end
$scope module pe_inst $end
$var wire 16 I" a_in [15:0] $end
$var wire 16 J" b_in [15:0] $end
$var wire 1 # clk $end
$var wire 1 $ reset $end
$var wire 1 E" valid_in $end
$var wire 32 K" mult [31:0] $end
$var parameter 32 L" DATA_WIDTH $end
$var reg 16 M" a_out [15:0] $end
$var reg 16 N" b_out [15:0] $end
$var reg 32 O" c_out [31:0] $end
$var reg 1 P" valid_out $end
$upscope $end
$upscope $end
$scope begin COL[3] $end
$var wire 1 Q" valid_in_local $end
$var wire 16 R" b_in_local [15:0] $end
$var wire 16 S" a_in_local [15:0] $end
$var parameter 3 T" j $end
$scope begin genblk1 $end
$upscope $end
$scope begin genblk2 $end
$upscope $end
$scope begin genblk3 $end
$upscope $end
$scope module pe_inst $end
$var wire 16 U" a_in [15:0] $end
$var wire 16 V" b_in [15:0] $end
$var wire 1 # clk $end
$var wire 1 $ reset $end
$var wire 1 Q" valid_in $end
$var wire 32 W" mult [31:0] $end
$var parameter 32 X" DATA_WIDTH $end
$var reg 16 Y" a_out [15:0] $end
$var reg 16 Z" b_out [15:0] $end
$var reg 32 [" c_out [31:0] $end
$var reg 1 \" valid_out $end
$upscope $end
$upscope $end
$upscope $end
$scope begin ROW[3] $end
$var parameter 3 ]" i $end
$scope begin COL[0] $end
$var wire 1 ^" valid_in_local $end
$var wire 16 _" b_in_local [15:0] $end
$var wire 16 `" a_in_local [15:0] $end
$var parameter 2 a" j $end
$scope begin genblk1 $end
$upscope $end
$scope begin genblk2 $end
$upscope $end
$scope begin genblk3 $end
$upscope $end
$scope module pe_inst $end
$var wire 16 b" a_in [15:0] $end
$var wire 16 c" b_in [15:0] $end
$var wire 1 # clk $end
$var wire 1 $ reset $end
$var wire 1 ^" valid_in $end
$var wire 32 d" mult [31:0] $end
$var parameter 32 e" DATA_WIDTH $end
$var reg 16 f" a_out [15:0] $end
$var reg 16 g" b_out [15:0] $end
$var reg 32 h" c_out [31:0] $end
$var reg 1 i" valid_out $end
$upscope $end
$upscope $end
$scope begin COL[1] $end
$var wire 1 j" valid_in_local $end
$var wire 16 k" b_in_local [15:0] $end
$var wire 16 l" a_in_local [15:0] $end
$var parameter 2 m" j $end
$scope begin genblk1 $end
$upscope $end
$scope begin genblk2 $end
$upscope $end
$scope begin genblk3 $end
$upscope $end
$scope module pe_inst $end
$var wire 16 n" a_in [15:0] $end
$var wire 16 o" b_in [15:0] $end
$var wire 1 # clk $end
$var wire 1 $ reset $end
$var wire 1 j" valid_in $end
$var wire 32 p" mult [31:0] $end
$var parameter 32 q" DATA_WIDTH $end
$var reg 16 r" a_out [15:0] $end
$var reg 16 s" b_out [15:0] $end
$var reg 32 t" c_out [31:0] $end
$var reg 1 u" valid_out $end
$upscope $end
$upscope $end
$scope begin COL[2] $end
$var wire 1 v" valid_in_local $end
$var wire 16 w" b_in_local [15:0] $end
$var wire 16 x" a_in_local [15:0] $end
$var parameter 3 y" j $end
$scope begin genblk1 $end
$upscope $end
$scope begin genblk2 $end
$upscope $end
$scope begin genblk3 $end
$upscope $end
$scope module pe_inst $end
$var wire 16 z" a_in [15:0] $end
$var wire 16 {" b_in [15:0] $end
$var wire 1 # clk $end
$var wire 1 $ reset $end
$var wire 1 v" valid_in $end
$var wire 32 |" mult [31:0] $end
$var parameter 32 }" DATA_WIDTH $end
$var reg 16 ~" a_out [15:0] $end
$var reg 16 !# b_out [15:0] $end
$var reg 32 "# c_out [31:0] $end
$var reg 1 ## valid_out $end
$upscope $end
$upscope $end
$scope begin COL[3] $end
$var wire 1 $# valid_in_local $end
$var wire 16 %# b_in_local [15:0] $end
$var wire 16 &# a_in_local [15:0] $end
$var parameter 3 '# j $end
$scope begin genblk1 $end
$upscope $end
$scope begin genblk2 $end
$upscope $end
$scope begin genblk3 $end
$upscope $end
$scope module pe_inst $end
$var wire 16 (# a_in [15:0] $end
$var wire 16 )# b_in [15:0] $end
$var wire 1 # clk $end
$var wire 1 $ reset $end
$var wire 1 $# valid_in $end
$var wire 32 *# mult [31:0] $end
$var parameter 32 +# DATA_WIDTH $end
$var reg 16 ,# a_out [15:0] $end
$var reg 16 -# b_out [15:0] $end
$var reg 32 .# c_out [31:0] $end
$var reg 1 /# valid_out $end
$upscope $end
$upscope $end
$upscope $end
$upscope $end
$upscope $end
$enddefinitions $end
$comment Show the parameter values. $end
$dumpall
b10000 +#
b11 '#
b10000 }"
b10 y"
b10000 q"
b1 m"
b10000 e"
b0 a"
b11 ]"
b10000 X"
b11 T"
b10000 L"
b10 H"
b10000 @"
b1 <"
b10000 4"
b0 0"
b10 ,"
b10000 '"
b11 #"
b10000 y
b10 u
b10000 m
b1 i
b10000 a
b0 ]
b1 Y
b10000 T
b11 P
b10000 H
b10 D
b10000 <
b1 8
b10000 0
b0 ,
b0 (
b10000 '
b10000 "
$end
#0
$dumpvars
x/#
bx .#
bx -#
bx ,#
bx *#
bx )#
bx (#
bx &#
bx %#
x$#
x##
bx "#
bx !#
bx ~"
bx |"
bx {"
bx z"
bx x"
bx w"
xv"
xu"
bx t"
bx s"
bx r"
bx p"
bx o"
bx n"
bx l"
bx k"
xj"
xi"
bx h"
bx g"
bx f"
bx d"
bx c"
b0 b"
b0 `"
bx _"
x^"
x\"
bx ["
bx Z"
bx Y"
bx W"
bx V"
bx U"
bx S"
bx R"
xQ"
xP"
bx O"
bx N"
bx M"
bx K"
bx J"
bx I"
bx G"
bx F"
xE"
xD"
bx C"
bx B"
bx A"
bx ?"
bx >"
bx ="
bx ;"
bx :"
x9"
x8"
bx 7"
bx 6"
bx 5"
bx 3"
bx 2"
b0 1"
b0 /"
bx ."
x-"
x+"
bx *"
bx )"
bx ("
bx &"
bx %"
bx $"
bx ""
bx !"
x~
x}
bx |
bx {
bx z
bx x
bx w
bx v
bx t
bx s
xr
xq
bx p
bx o
bx n
bx l
bx k
bx j
bx h
bx g
xf
xe
bx d
bx c
bx b
bx `
bx _
b0 ^
b0 \
bx [
xZ
xX
bx W
bx V
bx U
bx S
b0 R
bx Q
bx O
b0 N
xM
xL
bx K
bx J
bx I
bx G
b0 F
bx E
bx C
b0 B
xA
x@
bx ?
bx >
bx =
bx ;
b0 :
bx 9
bx 7
b0 6
x5
x4
bx 3
bx 2
bx 1
b0 /
b0 .
b0 -
b0 +
b0 *
0)
b100 &
0%
1$
0#
x!
$end
#5000
05
0Z
04
b0 3
0A
0@
b0 ?
0M
0L
b0 K
0X
b0 W
0f
0-"
0e
b0 d
0r
0q
b0 p
0~
0}
b0 |
0+"
b0 *"
09"
0^"
08"
b0 7"
0E"
0D"
b0 C"
0Q"
0P"
b0 O"
0\"
b0 ["
0j"
0i"
b0 h"
0v"
0u"
b0 t"
0$#
0##
b0 "#
0!
0/#
b0 .#
1#
#10000
0#
#15000
1#
#20000
0#
0$
#25000
b101 3
15
1Z
14
b1010 `
b101 [
b101 _
b101 2
b110 ;
b1 7
b1 9
b1 1
b1100 l
b110 g
b110 k
b110 >
b111 s
b111 w
b111 J
b1000 !"
b1000 %"
b1000 V
b10 h
b10 j
b10 b
b11 ;"
b11 ="
b11 5"
b100 l"
b100 n"
b100 f"
b1000 N
b1000 R
b111 B
b111 F
b110 6
b110 :
b101 /
b101 *
b101 .
b100 `"
b100 b"
b11 /"
b11 1"
b10 \
b10 ^
b1 +
b1 -
1)
1%
1#
#30000
0#
#35000
b100 x"
b100 z"
b100 r"
b10101 K"
b11 G"
b11 I"
b11 A"
b1000 R"
b1000 V"
b1000 )"
b111 F"
b111 J"
b111 {
b10010 ?"
b110 :"
b110 >"
b110 o
b1110 x
b10 t
b10 v
b10 n
b1010 d
1f
1-"
1e
b1111 3"
b101 ."
b101 2"
b101 c
b110 ?
1A
1@
b111 G
b1 C
b1 E
b1 =
b1010 3
0)
0%
1#
#40000
0#
#45000
05
0Z
04
b1100 ?
b111 K
1M
1L
b1000 S
b1 O
b1 Q
b1 I
b10100 d
b1100 p
1r
1q
b10000 &"
b10 ""
b10 $"
b10 z
b1111 7"
19"
1^"
18"
b10100 d"
b101 _"
b101 c"
b101 6"
b11000 p"
b110 k"
b110 o"
b110 B"
b11100 |"
b111 w"
b111 {"
b111 N"
b11000 W"
b11 S"
b11 U"
b11 M"
b100000 *#
b1000 %#
b1000 )#
b1000 Z"
b100 &#
b100 (#
b100 ~"
1#
#50000
0#
#55000
b1000 -#
b100 ,#
b111 !#
b110 s"
b10100 h"
1j"
1i"
b101 g"
b11 Y"
b10010 C"
1E"
1D"
b11110 7"
b10 ("
b1110 |
1~
1}
b11000 p
0f
0-"
0e
b1000 W
1X
b1 U
b1110 K
0A
0@
1#
#60000
0#
#65000
0M
0L
b10000 W
0r
0q
b11100 |
b10000 *"
1+"
09"
0^"
08"
b100100 C"
b10101 O"
1Q"
1P"
b101000 h"
b11000 t"
1v"
1u"
1#
#70000
0#
#75000
b11100 "#
1$#
1##
b110000 t"
0j"
0i"
b11000 ["
1\"
b101010 O"
0E"
0D"
b100000 *"
0~
0}
0X
1#
#80000
0#
#85000
0+"
0Q"
0P"
b110000 ["
0v"
0u"
b111000 "#
b100000 .#
1!
1/#
1#
#90000
0#
#95000
b1000000 .#
0$#
0##
0\"
1#
#100000
0#
#105000
0!
0/#
1#
